[
  {
    "InternalName": "apparently-it-s-my-fault-that-my-husband-has-the-head-of-a-beast-volume-1",
    "Chapters": [
      {
        "ChapterName": "Volume 1",
        "SortOrder": "1",
        "SubFolder": "",
        "OriginalFilenames": [],
        "Chapters": [
          {
            "ChapterName": "",
            "SortOrder": "101",
            "SubFolder": "",
            "OriginalFilenames": [
              "frontmatter1"
            ],
            "Chapters": []
          },
          {
            "ChapterName": "",
            "SortOrder": "102",
            "SubFolder": "",
            "OriginalFilenames": [
              "frontmatter2"
            ],
            "Chapters": []
          },
          {
            "ChapterName": "",
            "SortOrder": "103",
            "SubFolder": "",
            "OriginalFilenames": [
              "frontmatter3"
            ],
            "Chapters": []
          },
          {
            "ChapterName": "Prologue",
            "SortOrder": "104",
            "SubFolder": "",
            "OriginalFilenames": [
              "prologue"
            ],
            "Chapters": []
          },
          {
            "ChapterName": "Chapter 1: The Shut-In Princess Goes to an Evening Gala",
            "SortOrder": "105",
            "SubFolder": "",
            "OriginalFilenames": [
              "chapter1"
            ],
            "Chapters": []
          },
          {
            "ChapterName": "Chapter 2: Matrimony Mired in Objections",
            "SortOrder": "106",
            "SubFolder": "",
            "OriginalFilenames": [
              "chapter2",
              "insert1"
            ],
            "Chapters": []
          },
          {
            "ChapterName": "",
            "SortOrder": "107",
            "SubFolder": "",
            "OriginalFilenames": [
              "chapter21"
            ],
            "Chapters": []
          },
          {
            "ChapterName": "Chapter 3: Newlywed Life is Tumultuous",
            "SortOrder": "108",
            "SubFolder": "",
            "OriginalFilenames": [
              "chapter3",
              "insert2"
            ],
            "Chapters": []
          },
          {
            "ChapterName": "",
            "SortOrder": "109",
            "SubFolder": "",
            "OriginalFilenames": [
              "chapter31",
              "insert3"
            ],
            "Chapters": []
          },
          {
            "ChapterName": "",
            "SortOrder": "110",
            "SubFolder": "",
            "OriginalFilenames": [
              "chapter32"
            ],
            "Chapters": []
          },
          {
            "ChapterName": "Chapter 4: How to Crack a Difficult Heart",
            "SortOrder": "111",
            "SubFolder": "",
            "OriginalFilenames": [
              "chapter4",
              "insert4"
            ],
            "Chapters": []
          },
          {
            "ChapterName": "",
            "SortOrder": "112",
            "SubFolder": "",
            "OriginalFilenames": [
              "chapter41"
            ],
            "Chapters": []
          },
          {
            "ChapterName": "Chapter 5: Sweet Poison\u2019s Identity",
            "SortOrder": "113",
            "SubFolder": "",
            "OriginalFilenames": [
              "chapter5",
              "insert5"
            ],
            "Chapters": []
          },
          {
            "ChapterName": "",
            "SortOrder": "114",
            "SubFolder": "",
            "OriginalFilenames": [
              "chapter51"
            ],
            "Chapters": []
          },
          {
            "ChapterName": "Chapter 6: Tale of the Sacred Beast in the Forbidden Forest",
            "SortOrder": "115",
            "SubFolder": "",
            "OriginalFilenames": [
              "chapter6",
              "insert6"
            ],
            "Chapters": []
          },
          {
            "ChapterName": "",
            "SortOrder": "116",
            "SubFolder": "",
            "OriginalFilenames": [
              "chapter61",
              "insert7"
            ],
            "Chapters": []
          },
          {
            "ChapterName": "",
            "SortOrder": "117",
            "SubFolder": "",
            "OriginalFilenames": [
              "chapter62"
            ],
            "Chapters": []
          },
          {
            "ChapterName": "Epilogue",
            "SortOrder": "118",
            "SubFolder": "",
            "OriginalFilenames": [
              "epilogue",
              "insert8"
            ],
            "Chapters": []
          },
          {
            "ChapterName": "",
            "SortOrder": "119",
            "SubFolder": "",
            "OriginalFilenames": [
              "epilogue1"
            ],
            "Chapters": []
          },
          {
            "ChapterName": "Afterword",
            "SortOrder": "120",
            "SubFolder": "",
            "OriginalFilenames": [
              "afterword"
            ],
            "Chapters": []
          },
          {
            "ChapterName": "",
            "SortOrder": "121",
            "SubFolder": "",
            "OriginalFilenames": [
              "bonus"
            ],
            "Chapters": []
          },
          {
            "ChapterName": "",
            "SortOrder": "122",
            "SubFolder": "",
            "OriginalFilenames": [
              "signup"
            ],
            "Chapters": []
          },
          {
            "ChapterName": "",
            "SortOrder": "",
            "SubFolder": "",
            "OriginalFilenames": [
              "copyright"
            ],
            "Chapters": []
          }
        ]
      }
    ],
    "BonusChapters": [
      {
        "ChapterName": "Volume 1",
        "SortOrder": "1",
        "SubFolder": "",
        "OriginalFilenames": [],
        "Chapters": []
      }
    ],
    "ExtraContent": [],
    "Gallery": {
      "SplashImages": [
        "bonus",
        "cover",
        "frontmatter1",
        "frontmatter2",
        "frontmatter3",
        "jnovelclubrgb"
      ],
      "ChapterImages": [
        "insert1",
        "insert2",
        "insert3",
        "insert4",
        "insert5",
        "insert6",
        "insert7",
        "insert8"
      ],
      "ChapterName": "",
      "SortOrder": "",
      "SubFolder": "1-Volume 1",
      "OriginalFilenames": [],
      "Chapters": []
    }
  },
  {
    "InternalName": "apparently-it-s-my-fault-that-my-husband-has-the-head-of-a-beast-volume-2",
    "Chapters": [
      {
        "ChapterName": "Volume 2",
        "SortOrder": "2",
        "SubFolder": "",
        "OriginalFilenames": [],
        "Chapters": [
          {
            "ChapterName": "",
            "SortOrder": "201",
            "SubFolder": "",
            "OriginalFilenames": [
              "frontmatter1"
            ],
            "Chapters": []
          },
          {
            "ChapterName": "",
            "SortOrder": "202",
            "SubFolder": "",
            "OriginalFilenames": [
              "frontmatter2"
            ],
            "Chapters": []
          },
          {
            "ChapterName": "",
            "SortOrder": "203",
            "SubFolder": "",
            "OriginalFilenames": [
              "frontmatter3"
            ],
            "Chapters": []
          },
          {
            "ChapterName": "Prologue",
            "SortOrder": "204",
            "SubFolder": "",
            "OriginalFilenames": [
              "prologue"
            ],
            "Chapters": []
          },
          {
            "ChapterName": "Chapter 1: The Honeymoon Trip that Triggers Turmoil",
            "SortOrder": "205",
            "SubFolder": "",
            "OriginalFilenames": [
              "chapter1",
              "insert1"
            ],
            "Chapters": []
          },
          {
            "ChapterName": "",
            "SortOrder": "206",
            "SubFolder": "",
            "OriginalFilenames": [
              "chapter11"
            ],
            "Chapters": []
          },
          {
            "ChapterName": "Chapter 2: The Light and Darkness of the Underground Church",
            "SortOrder": "207",
            "SubFolder": "",
            "OriginalFilenames": [
              "chapter2",
              "insert2"
            ],
            "Chapters": []
          },
          {
            "ChapterName": "",
            "SortOrder": "208",
            "SubFolder": "",
            "OriginalFilenames": [
              "chapter21"
            ],
            "Chapters": []
          },
          {
            "ChapterName": "Chapter 3: The Labyrinthine Workings of the Church",
            "SortOrder": "209",
            "SubFolder": "",
            "OriginalFilenames": [
              "chapter3",
              "insert3"
            ],
            "Chapters": []
          },
          {
            "ChapterName": "",
            "SortOrder": "210",
            "SubFolder": "",
            "OriginalFilenames": [
              "chapter31"
            ],
            "Chapters": []
          },
          {
            "ChapterName": "Chapter 4: That Which Goes Seen and Unseen",
            "SortOrder": "211",
            "SubFolder": "",
            "OriginalFilenames": [
              "chapter4",
              "insert4"
            ],
            "Chapters": []
          },
          {
            "ChapterName": "",
            "SortOrder": "212",
            "SubFolder": "",
            "OriginalFilenames": [
              "chapter41"
            ],
            "Chapters": []
          },
          {
            "ChapterName": "Chapter 5: The Voiceless Speaker",
            "SortOrder": "213",
            "SubFolder": "",
            "OriginalFilenames": [
              "chapter5",
              "insert5"
            ],
            "Chapters": []
          },
          {
            "ChapterName": "",
            "SortOrder": "214",
            "SubFolder": "",
            "OriginalFilenames": [
              "chapter51",
              "insert6"
            ],
            "Chapters": []
          },
          {
            "ChapterName": "",
            "SortOrder": "215",
            "SubFolder": "",
            "OriginalFilenames": [
              "chapter52",
              "insert7"
            ],
            "Chapters": []
          },
          {
            "ChapterName": "",
            "SortOrder": "216",
            "SubFolder": "",
            "OriginalFilenames": [
              "chapter53",
              "insert8"
            ],
            "Chapters": []
          },
          {
            "ChapterName": "",
            "SortOrder": "217",
            "SubFolder": "",
            "OriginalFilenames": [
              "chapter54",
              "insert9"
            ],
            "Chapters": []
          },
          {
            "ChapterName": "",
            "SortOrder": "218",
            "SubFolder": "",
            "OriginalFilenames": [
              "chapter55"
            ],
            "Chapters": []
          },
          {
            "ChapterName": "Epilogue",
            "SortOrder": "219",
            "SubFolder": "",
            "OriginalFilenames": [
              "epilogue",
              "insert10"
            ],
            "Chapters": []
          },
          {
            "ChapterName": "",
            "SortOrder": "220",
            "SubFolder": "",
            "OriginalFilenames": [
              "epilogue1"
            ],
            "Chapters": []
          },
          {
            "ChapterName": "Afterword",
            "SortOrder": "221",
            "SubFolder": "",
            "OriginalFilenames": [
              "afterword"
            ],
            "Chapters": []
          },
          {
            "ChapterName": "",
            "SortOrder": "222",
            "SubFolder": "",
            "OriginalFilenames": [
              "bonus"
            ],
            "Chapters": []
          },
          {
            "ChapterName": "",
            "SortOrder": "223",
            "SubFolder": "",
            "OriginalFilenames": [
              "signup"
            ],
            "Chapters": []
          },
          {
            "ChapterName": "",
            "SortOrder": "",
            "SubFolder": "",
            "OriginalFilenames": [
              "copyright"
            ],
            "Chapters": []
          }
        ]
      }
    ],
    "BonusChapters": [
      {
        "ChapterName": "Volume 2",
        "SortOrder": "2",
        "SubFolder": "",
        "OriginalFilenames": [],
        "Chapters": []
      }
    ],
    "ExtraContent": [],
    "Gallery": {
      "SplashImages": [
        "bonus",
        "cover",
        "frontmatter1",
        "frontmatter2",
        "frontmatter3",
        "jnovelclubrgb"
      ],
      "ChapterImages": [
        "insert1",
        "insert10",
        "insert2",
        "insert3",
        "insert4",
        "insert5",
        "insert6",
        "insert7",
        "insert8",
        "insert9"
      ],
      "ChapterName": "",
      "SortOrder": "",
      "SubFolder": "2-Volume 2",
      "OriginalFilenames": [],
      "Chapters": []
    }
  }
]